libcbm/__init__.py
libcbm/input/__init__.py
libcbm/input/sit/__init__.py
libcbm/input/sit/sit.py
libcbm/input/sit/sit_age_class_parser.py
libcbm/input/sit/sit_cbm_config.py
libcbm/input/sit/sit_cbm_defaults.py
libcbm/input/sit/sit_cbm_factory.py
libcbm/input/sit/sit_classifier_parser.py
libcbm/input/sit/sit_disturbance_event_parser.py
libcbm/input/sit/sit_disturbance_type_parser.py
libcbm/input/sit/sit_eligbility_parser.py
libcbm/input/sit/sit_format.py
libcbm/input/sit/sit_inventory_parser.py
libcbm/input/sit/sit_mapping.py
libcbm/input/sit/sit_parser.py
libcbm/input/sit/sit_reader.py
libcbm/input/sit/sit_transition_rule_parser.py
libcbm/input/sit/sit_yield_parser.py
libcbm/model/__init__.py
libcbm/model/cbm/__init__.py
libcbm/model/cbm/cbm_config.py
libcbm/model/cbm/cbm_defaults.py
libcbm/model/cbm/cbm_defaults_reference.py
libcbm/model/cbm/cbm_factory.py
libcbm/model/cbm/cbm_model.py
libcbm/model/cbm/cbm_output.py
libcbm/model/cbm/cbm_simulator.py
libcbm/model/cbm/cbm_temperature_processor.py
libcbm/model/cbm/cbm_variables.py
libcbm/model/cbm/stand_cbm_factory.py
libcbm/model/cbm/rule_based/__init__.py
libcbm/model/cbm/rule_based/classifier_filter.py
libcbm/model/cbm/rule_based/event_processor.py
libcbm/model/cbm/rule_based/rule_filter.py
libcbm/model/cbm/rule_based/rule_target.py
libcbm/model/cbm/rule_based/transition_rule_processor.py
libcbm/model/cbm/rule_based/sit/__init__.py
libcbm/model/cbm/rule_based/sit/sit_event_processor.py
libcbm/model/cbm/rule_based/sit/sit_rule_based_processor.py
libcbm/model/cbm/rule_based/sit/sit_rule_based_sort.py
libcbm/model/cbm/rule_based/sit/sit_stand_filter.py
libcbm/model/cbm/rule_based/sit/sit_stand_target.py
libcbm/model/cbm/rule_based/sit/sit_transition_rule_processor.py
libcbm/model/cbm_exn/__init__.py
libcbm/model/cbm_exn/cbm_exn_annual_process_dynamics.py
libcbm/model/cbm_exn/cbm_exn_disturbance_dynamics.py
libcbm/model/cbm_exn/cbm_exn_growth_functions.py
libcbm/model/cbm_exn/cbm_exn_land_state.py
libcbm-2.9.2.dist-info/licenses/LICENSE
libcbm-2.9.2.dist-info/METADATA
libcbm-2.9.2.dist-info/WHEEL
libcbm-2.9.2.dist-info/top_level.txt
libcbm-2.9.2.dist-info/RECORD
